lightning_sam/__init__.py
lightning_sam/config.py
lightning_sam/dataset.py
lightning_sam/losses.py
lightning_sam/model.py
lightning_sam/train.py
lightning_sam/utils.py
wow_ai_sam-0.0.2.dist-info/LICENSE
wow_ai_sam-0.0.2.dist-info/METADATA
wow_ai_sam-0.0.2.dist-info/WHEEL
wow_ai_sam-0.0.2.dist-info/RECORD
