Metadata-Version: 2.1
Name: wow-ai-sam
Version: 0.0.2
Summary: Finetune segment-anything
Home-page: https://github.com/wow-ai-ml/wow-ai-segment-anything
License: LICENSE
Author: Tony shark
Author-email: quoi@wow-ai.com
Requires-Python: >=3.8,<3.11
Classifier: License :: Other/Proprietary License
Classifier: Programming Language :: Python :: 3
Classifier: Programming Language :: Python :: 3.8
Classifier: Programming Language :: Python :: 3.9
Classifier: Programming Language :: Python :: 3.10
Requires-Dist: Pillow (==9.3.0)
Requires-Dist: lightning (>=2.0.1,<3.0.0)
Requires-Dist: numpy (>=1.24.2,<2.0.0)
Requires-Dist: opencv_python (>=4.7.0.72,<5.0.0.0)
Requires-Dist: pycocotools (>=2.0.6,<3.0.0)
Requires-Dist: python-box (>=7.0.1,<8.0.0)
Requires-Dist: segment-anything (==1.0)
Requires-Dist: segmentation-models-pytorch (>=0.3.2,<0.4.0)
Requires-Dist: torch (>=2.0.0,<3.0.0)
Requires-Dist: torchvision (>=0.15.1,<0.16.0)
Project-URL: Repository, https://github.com/wow-ai-ml/wow-ai-segment-anything
